cax/__init__.py
cax/types.py
cax/core/__init__.py
cax/core/cs.py
cax/core/perceive/__init__.py
cax/core/perceive/conv_perceive.py
cax/core/perceive/kernels.py
cax/core/perceive/moore_perceive.py
cax/core/perceive/perceive.py
cax/core/perceive/von_neumann_perceive.py
cax/core/update/__init__.py
cax/core/update/mlp_update.py
cax/core/update/nca_update.py
cax/core/update/residual_update.py
cax/core/update/update.py
cax/cs/__init__.py
cax/cs/boids/__init__.py
cax/cs/boids/cs.py
cax/cs/boids/perceive.py
cax/cs/boids/perception.py
cax/cs/boids/policy.py
cax/cs/boids/state.py
cax/cs/boids/update.py
cax/cs/elementary/__init__.py
cax/cs/elementary/cs.py
cax/cs/elementary/perceive.py
cax/cs/elementary/update.py
cax/cs/flow_lenia/__init__.py
cax/cs/flow_lenia/cs.py
cax/cs/flow_lenia/update.py
cax/cs/lenia/__init__.py
cax/cs/lenia/cs.py
cax/cs/lenia/growth.py
cax/cs/lenia/kernel.py
cax/cs/lenia/metrics.py
cax/cs/lenia/perceive.py
cax/cs/lenia/rule.py
cax/cs/lenia/update.py
cax/cs/lenia/patterns/5N7KKM/pattern.pickle
cax/cs/lenia/patterns/5N7KKM/rule_params.pickle
cax/cs/lenia/patterns/5N7KKM_gyrating/pattern.pickle
cax/cs/lenia/patterns/5N7KKM_gyrating/rule_params.pickle
cax/cs/lenia/patterns/5N7KKM_twin/pattern.pickle
cax/cs/lenia/patterns/5N7KKM_twin/rule_params.pickle
cax/cs/lenia/patterns/Gyrorbium/pattern.pickle
cax/cs/lenia/patterns/Gyrorbium/rule_params.pickle
cax/cs/lenia/patterns/Orbium/pattern.pickle
cax/cs/lenia/patterns/Orbium/rule_params.pickle
cax/cs/lenia/patterns/VT049W/pattern.pickle
cax/cs/lenia/patterns/VT049W/rule_params.pickle
cax/cs/life/__init__.py
cax/cs/life/cs.py
cax/cs/life/perceive.py
cax/cs/life/update.py
cax/cs/particle_lenia/__init__.py
cax/cs/particle_lenia/cs.py
cax/cs/particle_lenia/growth.py
cax/cs/particle_lenia/kernel.py
cax/cs/particle_lenia/perceive.py
cax/cs/particle_lenia/rule.py
cax/cs/particle_lenia/update.py
cax/cs/particle_life/__init__.py
cax/cs/particle_life/cs.py
cax/cs/particle_life/perceive.py
cax/cs/particle_life/perception.py
cax-0.3.3.dist-info/METADATA
cax-0.3.3.dist-info/WHEEL
cax-0.3.3.dist-info/licenses/LICENSE
cax-0.3.3.dist-info/RECORD
