Metadata-Version: 2.4
Name: cax
Version: 0.3.3
Summary: Cellular Automata Accelerated in JAX
Project-URL: Homepage, https://github.com/maxencefaldor/cax
Project-URL: Documentation, https://maxencefaldor.github.io/cax/
Author-email: Maxence Faldor <maxencefaldor@gmail.com>
License-Expression: MIT
License-File: LICENSE
Keywords: artificial life,cellular automata,complex systems,emergence,neural cellular automata,open-endedness,self-organization
Classifier: License :: OSI Approved :: MIT License
Classifier: Operating System :: OS Independent
Classifier: Programming Language :: Python :: 3.11
Classifier: Programming Language :: Python :: 3.12
Classifier: Programming Language :: Python :: 3.13
Requires-Python: >=3.11
Requires-Dist: flax>=0.12.0
Requires-Dist: jax>=0.8.0
Requires-Dist: optax>=0.2.0
Requires-Dist: pillow>=11.1.0
Provides-Extra: dev
Requires-Dist: mypy>=1.11.0; extra == 'dev'
Requires-Dist: pytest-cov>=5.0.0; extra == 'dev'
Requires-Dist: pytest>=8.3.0; extra == 'dev'
Requires-Dist: ruff>=0.6.0; extra == 'dev'
Provides-Extra: docs
Requires-Dist: mkdocs; extra == 'docs'
Requires-Dist: mkdocs-jupyter; extra == 'docs'
Requires-Dist: mkdocs-material; extra == 'docs'
Requires-Dist: mkdocstrings[python]; extra == 'docs'
Provides-Extra: examples
Requires-Dist: evosax>=0.2.0; extra == 'examples'
Requires-Dist: ipykernel>=6.29.0; extra == 'examples'
Requires-Dist: ipywidgets>=8.1.0; extra == 'examples'
Requires-Dist: mediapy>=1.2.0; extra == 'examples'
Requires-Dist: torchvision>=0.21.0; extra == 'examples'
Requires-Dist: tqdm>=4.67.0; extra == 'examples'
